{"pageProps":{"article":{"id":1136,"wordId":"","title":"letters jo","synthesis":"","phonemic":"","image":"","urlimage":"","audio":"/resourses/ftm/spanish/sounds/letters/jo.wav","urlaudio":"https://edupix.io/resourses/ftm/spanish/sounds/letters/jo.wav","learninglevel":"","simpleWord":"","sightWord":"","phonicsWord":"","inlanguage":"es","contenttype":"Audio","author":"Curious Learning","publisher":"Curious Learning","licenseurl":"https://creativecommons.org/licenses/by/4.0/","license":"CC-BY-4.0","featured":"no","usedin":"","educationalrole":"Early Grades","tags":""}},"__N_SSG":true}