{"pageProps":{"article":{"id":2468,"wordId":"house","title":"house","synthesis":"","phonemic":"h/au/s","image":"/resourses/wch/uganda/img/WordImage_house.png","urlimage":"https://edupix.io/resourses/wch/uganda/img/WordImage_house.png","audio":"/resourses/wch/uganda/audio/h-q/WordAudio_house.ogg","urlaudio":"https://edupix.io/resourses/wch/uganda/audio/h-q/WordAudio_house.ogg","learninglevel":100,"simpleWord":"N","sightWord":"N","phonicsWord":"N","inlanguage":"en-ug","contenttype":"","author":"War Child","publisher":"War Child","licenseurl":"https://creativecommons.org/licenses/by/4.0/","license":"CC-BY-4.0","featured":"no","usedin":"","educationalrole":"Early Grades","tags":""}},"__N_SSG":true}