{"pageProps":{"article":{"id":3269,"wordId":"soak","title":"soak","synthesis":"s/oa/k","phonemic":"s/..u/k","image":"","urlimage":"","audio":"/resourses/wch/uganda/audio/r-z/WordAudio_soak.ogg","urlaudio":"https://edupix.io/resourses/wch/uganda/audio/r-z/WordAudio_soak.ogg","learninglevel":37,"simpleWord":"Y","sightWord":"N","phonicsWord":"Y","inlanguage":"en-ug","contenttype":"","author":"War Child","publisher":"War Child","licenseurl":"https://creativecommons.org/licenses/by/4.0/","license":"CC-BY-4.0","featured":"no","usedin":"","educationalrole":"Early Grades","tags":""}},"__N_SSG":true}