{"pageProps":{"article":{"id":3559,"wordId":"took","title":"took","synthesis":"t/oo/k","phonemic":"t/u/k","image":"","urlimage":"","audio":"/resourses/wch/uganda/audio/r-z/WordAudio_took.ogg","urlaudio":"https://edupix.io/resourses/wch/uganda/audio/r-z/WordAudio_took.ogg","learninglevel":40,"simpleWord":"Y","sightWord":"N","phonicsWord":"Y","inlanguage":"en-ug","contenttype":"","author":"War Child","publisher":"War Child","licenseurl":"https://creativecommons.org/licenses/by/4.0/","license":"CC-BY-4.0","featured":"no","usedin":"","educationalrole":"Early Grades","tags":""}},"__N_SSG":true}