{"pageProps":{"article":{"id":3627,"wordId":"up","title":"up","synthesis":"u/p","phonemic":"^/p","image":"/resourses/wch/uganda/img/WordImage_up.png","urlimage":"https://edupix.io/resourses/wch/uganda/img/WordImage_up.png","audio":"/resourses/wch/uganda/audio/r-z/WordAudio_up.ogg","urlaudio":"https://edupix.io/resourses/wch/uganda/audio/r-z/WordAudio_up.ogg","learninglevel":15,"simpleWord":"Y","sightWord":"N","phonicsWord":"Y","inlanguage":"en-ug","contenttype":"","author":"War Child","publisher":"War Child","licenseurl":"https://creativecommons.org/licenses/by/4.0/","license":"CC-BY-4.0","featured":"no","usedin":"","educationalrole":"Early Grades","tags":""}},"__N_SSG":true}