{"pageProps":{"article":{"id":3725,"wordId":"wool","title":"wool","synthesis":"w/oo/l","phonemic":"w/u/l","image":"/resourses/wch/uganda/img/WordImage_wool.png","urlimage":"https://edupix.io/resourses/wch/uganda/img/WordImage_wool.png","audio":"/resourses/wch/uganda/audio/r-z/WordAudio_wool.ogg","urlaudio":"https://edupix.io/resourses/wch/uganda/audio/r-z/WordAudio_wool.ogg","learninglevel":40,"simpleWord":"Y","sightWord":"N","phonicsWord":"Y","inlanguage":"en-ug","contenttype":"","author":"War Child","publisher":"War Child","licenseurl":"https://creativecommons.org/licenses/by/4.0/","license":"CC-BY-4.0","featured":"no","usedin":"","educationalrole":"Early Grades","tags":""}},"__N_SSG":true}